Pointa/__init__.py
Pointa/Client/Game.py
Pointa/Client/__init__.py
Pointa/Client/locales/__init__.py
Pointa/Client/locales/en_US.py
Pointa/Client/locales/zh_CN.py
Pointa/Server/DynamicEventLoop.py
Pointa/Server/Pointa.py
Pointa/Server/__init__.py
Pointa/Server/__main__.py
Pointa/Server/app.py
Pointa/Server/configs/Config.py
Pointa/Server/configs/__init__.py
Pointa-0.2.33.dist-info/LICENSE
Pointa-0.2.33.dist-info/METADATA
Pointa-0.2.33.dist-info/WHEEL
Pointa-0.2.33.dist-info/top_level.txt
Pointa-0.2.33.dist-info/RECORD
