Metadata-Version: 2.1
Name: Pointa
Version: 0.2.33
Summary: Pointa Dedicated Server & CLI Based Client
Home-page: https://github.com/KRedCell/Pointa
Author: KRedCell
Author-email: krov_red_cell@outlook.com
License: UNKNOWN
Platform: UNKNOWN
Classifier: Programming Language :: Python :: 3
Classifier: License :: OSI Approved :: MIT License
Classifier: Operating System :: OS Independent
Requires-Python: >=3.7
Requires-Dist: gevent
Requires-Dist: Flask
Requires-Dist: requests
Requires-Dist: pickledb
